#ifndef BYTECODE
#define BYTECODE(CODE,VALUE)
#endif

BYTECODE(aaload, 0x32)
BYTECODE(aastore, 0x53)
BYTECODE(aconst_null, 0x01)
BYTECODE(aload, 0x19)
BYTECODE(aload_0, 0x2a)
BYTECODE(aload_1, 0x2b)
BYTECODE(aload_2, 0x2c)
BYTECODE(aload_3, 0x2d)
BYTECODE(anewarray, 0xbd)
BYTECODE(areturn, 0xb0)
BYTECODE(arraylength, 0xbe)
BYTECODE(astore, 0x3a)
BYTECODE(astore_0, 0x4b)
BYTECODE(astore_1, 0x4c)
BYTECODE(astore_2, 0x4d)
BYTECODE(astore_3, 0x4e)
BYTECODE(athrow, 0xbf)
BYTECODE(baload, 0x33)
BYTECODE(bastore, 0x54)
BYTECODE(bipush, 0x10)
BYTECODE(caload, 0x34)
BYTECODE(castore, 0x55)
BYTECODE(checkcast, 0xc0)
BYTECODE(d2f, 0x90)
BYTECODE(d2i, 0x8e)
BYTECODE(d2l, 0x8f)
BYTECODE(dadd, 0x63)
BYTECODE(daload, 0x31)
BYTECODE(dastore, 0x52)
BYTECODE(dcmpg, 0x98)
BYTECODE(dcmpl, 0x97)
BYTECODE(dconst_0, 0x0e)
BYTECODE(dconst_1, 0x0f)
BYTECODE(ddiv, 0x6f)
BYTECODE(dload, 0x18)
BYTECODE(dload_0, 0x26)
BYTECODE(dload_1, 0x27)
BYTECODE(dload_2, 0x28)
BYTECODE(dload_3, 0x29)
BYTECODE(dmul, 0x6b)
BYTECODE(dneg, 0x77)
BYTECODE(drem, 0x73)
BYTECODE(dreturn, 0xaf)
BYTECODE(dstore, 0x39)
BYTECODE(dstore_0, 0x47)
BYTECODE(dstore_1, 0x48)
BYTECODE(dstore_2, 0x49)
BYTECODE(dstore_3, 0x4a)
BYTECODE(dsub, 0x67)
BYTECODE(dup, 0x59)
BYTECODE(dup_x1, 0x5a)
BYTECODE(dup_x2, 0x5b)
BYTECODE(dup2, 0x5c)
BYTECODE(dup2_x1, 0x5d)
BYTECODE(dup2_x2, 0x5e)
BYTECODE(f2d, 0x8d)
BYTECODE(f2i, 0x8b)
BYTECODE(f2l, 0x8c)
BYTECODE(fadd, 0x62)
BYTECODE(faload, 0x30)
BYTECODE(fastore, 0x51)
BYTECODE(fcmpg, 0x96)
BYTECODE(fcmpl, 0x95)
BYTECODE(fconst_0, 0x0b)
BYTECODE(fconst_1, 0x0c)
BYTECODE(fconst_2, 0x0d)
BYTECODE(fdiv, 0x6e)
BYTECODE(fload, 0x17)
BYTECODE(fload_0, 0x22)
BYTECODE(fload_1, 0x23)
BYTECODE(fload_2, 0x24)
BYTECODE(fload_3, 0x25)
BYTECODE(fmul, 0x6a)
BYTECODE(fneg, 0x76)
BYTECODE(frem, 0x72)
BYTECODE(freturn, 0xae)
BYTECODE(fstore, 0x38)
BYTECODE(fstore_0, 0x43)
BYTECODE(fstore_1, 0x44)
BYTECODE(fstore_2, 0x45)
BYTECODE(fstore_3, 0x46)
BYTECODE(fsub, 0x66)
BYTECODE(getfield, 0xb4)
BYTECODE(getstatic, 0xb2)
BYTECODE(goto, 0xa7)
BYTECODE(goto_w, 0xc8)
BYTECODE(i2b, 0x91)
BYTECODE(i2c, 0x92)
BYTECODE(i2d, 0x87)
BYTECODE(i2f, 0x86)
BYTECODE(i2l, 0x85)
BYTECODE(i2s, 0x93)
BYTECODE(iadd, 0x60)
BYTECODE(iaload, 0x2e)
BYTECODE(iand, 0x7e)
BYTECODE(iastore, 0x4f)
BYTECODE(iconst_m1, 0x02)
BYTECODE(iconst_0, 0x03)
BYTECODE(iconst_1, 0x04)
BYTECODE(iconst_2, 0x05)
BYTECODE(iconst_3, 0x06)
BYTECODE(iconst_4, 0x07)
BYTECODE(iconst_5, 0x08)
BYTECODE(idiv, 0x6c)
BYTECODE(if_acmpeq, 0xa5)
BYTECODE(if_acmpne, 0xa6)
BYTECODE(if_icmpeq, 0x9f)
BYTECODE(if_icmpne, 0xa0)
BYTECODE(if_icmplt, 0xa1)
BYTECODE(if_icmpge, 0xa2)
BYTECODE(if_icmpgt, 0xa3)
BYTECODE(if_icmple, 0xa4)
BYTECODE(ifeq, 0x99)
BYTECODE(ifne, 0x9a)
BYTECODE(iflt, 0x9b)
BYTECODE(ifge, 0x9c)
BYTECODE(ifgt, 0x9d)
BYTECODE(ifle, 0x9e)
BYTECODE(ifnonnull, 0xc7)
BYTECODE(ifnull, 0xc6)
BYTECODE(iinc, 0x84)
BYTECODE(iload, 0x15)
BYTECODE(iload_0, 0x1a)
BYTECODE(iload_1, 0x1b)
BYTECODE(iload_2, 0x1c)
BYTECODE(iload_3, 0x1d)
BYTECODE(imul, 0x68)
BYTECODE(ineg, 0x74)
BYTECODE(instanceof, 0xc1)
BYTECODE(invokedynamic, 0xba)
BYTECODE(invokeinterface, 0xb9)
BYTECODE(invokespecial, 0xb7)
BYTECODE(invokestatic, 0xb8)
BYTECODE(invokevirtual, 0xb6)
BYTECODE(ior, 0x80)
BYTECODE(irem, 0x70)
BYTECODE(ireturn, 0xac)
BYTECODE(ishl, 0x78)
BYTECODE(ishr, 0x7a)
BYTECODE(istore, 0x36)
BYTECODE(istore_0, 0x3b)
BYTECODE(istore_1, 0x3c)
BYTECODE(istore_2, 0x3d)
BYTECODE(istore_3, 0x3e)
BYTECODE(isub, 0x64)
BYTECODE(iushr, 0x7c)
BYTECODE(ixor, 0x82)
BYTECODE(jsr, 0xa8)
BYTECODE(jsr_w, 0xc9)
BYTECODE(l2d, 0x8a)
BYTECODE(l2f, 0x89)
BYTECODE(l2i, 0x88)
BYTECODE(ladd, 0x61)
BYTECODE(laload, 0x2f)
BYTECODE(land, 0x7f)
BYTECODE(lastore, 0x50)
BYTECODE(lcmp, 0x94)
BYTECODE(lconst_0, 0x09)
BYTECODE(lconst_1, 0x0a)
BYTECODE(ldc, 0x12)
BYTECODE(ldc_w, 0x13)
BYTECODE(ldc2_w, 0x14)
BYTECODE(ldiv, 0x6d)
BYTECODE(lload, 0x16)
BYTECODE(lload_0, 0x1e)
BYTECODE(lload_1, 0x1f)
BYTECODE(lload_2, 0x20)
BYTECODE(lload_3, 0x21)
BYTECODE(lmul, 0x69)
BYTECODE(lneg, 0x75)
BYTECODE(lookupswitch, 0xab)
BYTECODE(lor, 0x81)
BYTECODE(lrem, 0x71)
BYTECODE(lreturn, 0xad)
BYTECODE(lshl, 0x79)
BYTECODE(lshr, 0x7b)
BYTECODE(lstore, 0x37)
BYTECODE(lstore_0, 0x3f)
BYTECODE(lstore_1, 0x40)
BYTECODE(lstore_2, 0x41)
BYTECODE(lstore_3, 0x42)
BYTECODE(lsub, 0x65)
BYTECODE(lushr, 0x7d)
BYTECODE(lxor, 0x83)
BYTECODE(monitorenter, 0xc2)
BYTECODE(monitorexit, 0xc3)
BYTECODE(multianewarray, 0xc5)
BYTECODE(new, 0xbb)
BYTECODE(newarray, 0xbc)
BYTECODE(nop, 0x00)
BYTECODE(pop, 0x57)
BYTECODE(pop2, 0x58)
BYTECODE(putfield, 0xb5)
BYTECODE(putstatic, 0xb3)
BYTECODE(ret, 0xa9)
BYTECODE(return, 0xb1)
BYTECODE(saload, 0x35)
BYTECODE(sastore, 0x56)
BYTECODE(sipush, 0x11)
BYTECODE(swap, 0x5f)
BYTECODE(tableswitch, 0xaa)
BYTECODE(wide, 0xc4)

#undef BYTECODE
