#ifndef R11F_BYTECODE_H
#define R11F_BYTECODE_H

#include "clsfile.h"
#include "defs.h"
#ifdef __cplusplus
extern "C" {
#endif

enum {
    R11F_aaload = 0x32,
    R11F_aastore = 0x53,
    R11F_aconst_null = 0x01,
    R11F_aload = 0x19,
    R11F_aload_0 = 0x2a,
    R11F_aload_1 = 0x2b,
    R11F_aload_2 = 0x2c,
    R11F_aload_3 = 0x2d,
    R11F_anewarray = 0xbd,
    R11F_areturn = 0xb0,
    R11F_arraylength = 0xbe,
    R11F_astore = 0x3a,
    R11F_astore_0 = 0x4b,
    R11F_astore_1 = 0x4c,
    R11F_astore_2 = 0x4d,
    R11F_astore_3 = 0x4e,
    R11F_athrow = 0xbf,

    R11F_baload = 0x33,
    R11F_bastore = 0x54,
    R11F_bipush = 0x10,

    R11F_caload = 0x34,
    R11F_castore = 0x55,
    R11F_checkcast = 0xc0,
    R11F_d2f = 0x90,
    R11F_d2i = 0x8e,
    R11F_d2l = 0x8f,
    R11F_dadd = 0x63,
    R11F_daload = 0x31,
    R11F_dastore = 0x52,
    R11F_dconst_0 = 0x0e,
    R11F_dconst_1 = 0x0f,
    R11F_ddiv = 0x6f,
    R11F_dload = 0x18,
    R11F_dload_0 = 0x26,
    R11F_dload_1 = 0x27,
    R11F_dload_2 = 0x28,
    R11F_dload_3 = 0x29,
    R11F_dmul = 0x6b,
    R11F_dneg = 0x77,
    R11F_drem = 0x73,
    R11F_dreturn = 0xaf,
    R11F_dstore = 0x39,
    R11F_dstore_0 = 0x47,
    R11F_dstore_1 = 0x48,
    R11F_dstore_2 = 0x49,
    R11F_dstore_3 = 0x4a,
    R11F_dsub = 0x67,
    R11F_dup = 0x59,
    R11F_dup_x1 = 0x5a,
    R11F_dup_x2 = 0x5b,
    R11F_dup2 = 0x5c,
    R11F_dup2_x1 = 0x5d,
    R11F_dup2_x2 = 0x5e,

    R11F_f2d = 0x8d,
    R11F_f2i = 0x8b,
    R11F_f2l = 0x8c,
    R11F_fadd = 0x62,
    R11F_faload = 0x30,
    R11F_fastore = 0x51,
    R11F_fcmpg = 0x96,
    R11F_fcmpl = 0x95,
    R11F_fconst_0 = 0x0b,
    R11F_fconst_1 = 0x0c,
    R11F_fconst_2 = 0x0d,
    R11F_fdiv = 0x6e,
    R11F_fload = 0x17,
    R11F_fload_0 = 0x22,
    R11F_fload_1 = 0x23,
    R11F_fload_2 = 0x24,
    R11F_fload_3 = 0x25,
    R11F_fmul = 0x6a,
    R11F_fneg = 0x76,
    R11F_frem = 0x72,
    R11F_freturn = 0xae,
    R11F_fstore = 0x38,
    R11F_fstore_0 = 0x43,
    R11F_fstore_1 = 0x44,
    R11F_fstore_2 = 0x45,
    R11F_fstore_3 = 0x46,
    R11F_fsub = 0x66,

    R11F_getfield = 0xb4,
    R11F_getstatic = 0xb2,

    R11F_goto = 0xa7,
    R11F_goto_w = 0xc8,

    R11F_i2b = 0x91,
    R11F_i2c = 0x92,
    R11F_i2d = 0x87,
    R11F_i2f = 0x86,
    R11F_i2l = 0x85,
    R11F_i2s = 0x93,
    R11F_iadd = 0x60,
    R11F_iaload = 0x2e,
    R11F_iand = 0x7e,
    R11F_iastore = 0x4f,
    R11F_iconst_m1 = 0x02,
    R11F_iconst_0 = 0x03,
    R11F_iconst_1 = 0x04,
    R11F_iconst_2 = 0x05,
    R11F_iconst_3 = 0x06,
    R11F_iconst_4 = 0x07,
    R11F_iconst_5 = 0x08,
    R11F_idiv = 0x6c,
    R11F_iinc = 0x84,
    R11F_iload = 0x15,
    R11F_iload_0 = 0x1a,
    R11F_iload_1 = 0x1b,
    R11F_iload_2 = 0x1c,
    R11F_iload_3 = 0x1d,
    R11F_imul = 0x68,
    R11F_ineg = 0x74,
    R11F_ior = 0x80,
    R11F_irem = 0x70,
    R11F_ireturn = 0xac,
    R11F_ishl = 0x78,
    R11F_ishr = 0x7a,
    R11F_istore = 0x36,
    R11F_istore_0 = 0x3b,
    R11F_istore_1 = 0x3c,
    R11F_istore_2 = 0x3d,
    R11F_istore_3 = 0x3e,
    R11F_isub = 0x64,
    R11F_ushr = 0x7c,
    R11F_ixor = 0x82,

    R11F_if_acmpeq = 0xa5,
    R11F_if_acmpne = 0xa6,
    R11F_if_icmpeq = 0x9f,
    R11F_if_icmpne = 0xa0,
    R11F_if_icmplt = 0xa1,
    R11F_if_icmpge = 0xa2,
    R11F_if_icmpgt = 0xa3,
    R11F_if_icmple = 0xa4,
    R11F_ifeq = 0x99,
    R11F_ifne = 0x9a,
    R11F_iflt = 0x9b,
    R11F_ifge = 0x9c,
    R11F_ifgt = 0x9d,
    R11F_ifle = 0x9e,
    R11F_ifnonnull = 0xc7,
    R11F_ifnull = 0xc6,

    R11F_instanceof = 0xc1,
    R11F_invokedynamic = 0xba,
    R11F_invokeinterface = 0xb9,
    R11F_invokespecial = 0xb7,
    R11F_invokestatic = 0xb8,
    R11F_invokevirtual = 0xb6,

    R11F_jsr = 0xa8,
    R11F_jsr_w = 0xc9,

    R11F_l2d = 0x8a,
    R11F_l2f = 0x89,
    R11F_l2i = 0x88,
    R11F_ladd = 0x61,
    R11F_laload = 0x2f,
    R11F_land = 0x7f,
    R11F_lastore = 0x50,
    R11F_lcmp = 0x94,
    R11F_lconst_0 = 0x09,
    R11F_lconst_1 = 0x0a,
    R11F_ldiv = 0x6d,
    R11F_lload = 0x16,
    R11F_lload_0 = 0x1e,
    R11F_lload_1 = 0x1f,
    R11F_lload_2 = 0x20,
    R11F_lload_3 = 0x21,
    R11F_lmul = 0x69,
    R11F_lneg = 0x75,
    R11F_lookupswitch = 0xab,
    R11F_lor = 0x81,
    R11F_lrem = 0x71,
    R11F_lreturn = 0xad,
    R11F_lshl = 0x79,
    R11F_lshr = 0x7b,
    R11F_lstore = 0x37,
    R11F_lstore_0 = 0x3f,
    R11F_lstore_1 = 0x40,
    R11F_lstore_2 = 0x41,
    R11F_lstore_3 = 0x42,
    R11F_lsub = 0x65,
    R11F_lushr = 0x7d,
    R11F_lxor = 0x83,

    R11F_ldc = 0x12,
    R11F_ldc_w = 0x13,
    R11F_ldc2_w = 0x14,

    R11F_monitorenter = 0xc2,
    R11F_monitorexit = 0xc3,
    R11F_multianewarray = 0xc5,

    R11F_new = 0xbb,
    R11F_newarray = 0xbc,
    R11F_nop = 0x00,

    R11F_pop = 0x57,
    R11F_pop2 = 0x58,
    R11F_putfield = 0xb5,
    R11F_putstatic = 0xb3,

    R11F_ret = 0xa9,
    R11F_return = 0xb1,

    R11F_saload = 0x35,
    R11F_sastore = 0x56,
    R11F_sipush = 0x11,
    R11F_swap = 0x5f,

    R11F_tableswitch = 0xaa,

    R11F_wide = 0xc4
};

#ifdef __cplusplus
} /* extern "C" */
#endif

#endif /* R11F_BYTECODE_H */
